{
  "version": 1,
  "serviceConfiguration": {
    "serviceName": "AppSync",
    "defaultAuthType": {
      "mode": "API_KEY",
      "expirationTime": 30,
      "apiKeyExpirationDate": "2022-09-04T22:17:12.097Z",
      "keyDescription": "api key description"
    },
    "conflictResolution": {
      "defaultResolutionStrategy": {
        "type": "AUTOMERGE"
      }
    },
    "apiName": "amplifyDatasource",
    "additionalAuthTypes": [
      {
        "mode": "AWS_IAM"
      }
    ],
    "gqlSchemaPath": "/Users/mcanela/Repositories/market-info-project/amplify/backend/api/amplifyDatasource/schema.graphql"
  }
}